Fittness/__init__.py
Fittness/test_nutrients.py
Fittness/test_visualization.py
Fittness/calories_burn/__init__.py
Fittness/calories_burn/monitoring.py
Fittness/calories_burn/records.py
Fittness/calories_burn/tempCodeRunnerFile.py
Fittness/calories_intake/__init__.py
Fittness/calories_intake/nutrients.py
Fittness/calories_intake/visualization.py
Fittness-1.2.dist-info/LICENSE.txt
Fittness-1.2.dist-info/METADATA
Fittness-1.2.dist-info/WHEEL
Fittness-1.2.dist-info/top_level.txt
Fittness-1.2.dist-info/RECORD
