Metadata-Version: 2.1
Name: Fittness
Version: 1.2
Summary: A test python package
Home-page: https://github.com/RaineShen/data533Lab4.git
Author: YuxuanIsme,raineShen
Author-email: cuiyuuxuan@gmail.com,rain.ya1213@gmail.com
License: MIT
Platform: UNKNOWN
Requires-Dist: bokeh
Requires-Dist: pygal
